[
  {
    "name": "ساعة منبه رقمية",
    "price": "150 شيكل",
    "phone": "0567772374",
    "address": "التفاح - شارع يافا",
    "description": "ساعة حديثة مع إضاءة ليلية ومنبه قوي",
    "image": "https://drive.google.com/thumbnail?id=14NkSNrlvalpifu1LFLLoqYbnS-75K5xK&sz=w800"
  },
  {
    "name": "سماعة بلوتوث",
    "price": "220 شيكل",
    "phone": "0599123456",
    "address": "غزة - الرمال",
    "description": "جودة صوت عالية، بطارية طويلة",
    "image": "https://drive.google.com/thumbnail?id=1AbCdEfGhIjKlMnOpQrStUvWxYz&sz=w800"
  }
]
